oauth_redirect/.gitignore
oauth_redirect/__init__.py
oauth_redirect/background.py
oauth_redirect/cli.py
oauth_redirect/server.py
oauth_redirect/tests/conftest.py
oauth_redirect/tests/test_server.py
oauth_redirect-0.3.0.dist-info/DESCRIPTION.rst
oauth_redirect-0.3.0.dist-info/METADATA
oauth_redirect-0.3.0.dist-info/RECORD
oauth_redirect-0.3.0.dist-info/WHEEL
oauth_redirect-0.3.0.dist-info/entry_points.txt
oauth_redirect-0.3.0.dist-info/metadata.json
oauth_redirect-0.3.0.dist-info/namespace_packages.txt
oauth_redirect-0.3.0.dist-info/top_level.txt
