Metadata-Version: 2.0
Name: oauth-redirect
Version: 0.3.0
Summary: Securely redirects OAuth responses to known clients.
Home-page: http://github.com/seantis/oauth_redirect
Author: Seantis GmbH
Author-email: info@seantis.ch
License: GPLv2
Platform: any
Classifier: Intended Audience :: Developers
Classifier: Programming Language :: Python
Classifier: Programming Language :: Python :: 3
Classifier: Topic :: Software Development :: Libraries :: Python Modules
Classifier: License :: OSI Approved :: GNU General Public License v2 (GPLv2)
Requires-Dist: aiohttp
Requires-Dist: click
Requires-Dist: purl
Provides-Extra: test
Requires-Dist: coverage; extra == 'test'
Requires-Dist: mirakuru; extra == 'test'
Requires-Dist: morepath; extra == 'test'
Requires-Dist: pytest; extra == 'test'
Requires-Dist: pytest-localserver; extra == 'test'
Requires-Dist: requests; extra == 'test'
